dcrf_asyncapi/__init__.py
dcrf_asyncapi/_settings_stub.py
dcrf_asyncapi/action_docs.py
dcrf_asyncapi/asyncapi.py
dcrf_asyncapi/introspect.py
dcrf_asyncapi/views.py
dcrf_asyncapi/templates/dcrf_asyncapi/index.html
dcrf_asyncapi-0.0.2.dist-info/WHEEL
dcrf_asyncapi-0.0.2.dist-info/METADATA
dcrf_asyncapi-0.0.2.dist-info/RECORD
