Metadata-Version: 2.1
Name: dcrf_asyncapi
Version: 0.0.2
Summary: AsyncAPI schema generation for Django Channels Rest Framework
Home-page: https://github.com/vskrachkov/dcrf-asyncapi
Author: Viacheslav Krachkov
Author-email: vskrachkov@gmail.com
Requires-Python: >=3.9
